Metadata-Version: 2.1
Name: tifffolder
Version: 0.1.7
Summary: Easily parse/access a subset of data from a <=6D folder of TIFFs
Home-page: https://github.com/tlambert03/tifffolder
Author: Talley Lambert
Author-email: talley.lambert@gmail.com
License: MIT
Project-URL: Code, https://github.com/tlambert03/tifffolder
Project-URL: Issue tracker, https://github.com/tlambert03/tifffolder/issues
Keywords: image,analysis,tiff
Platform: UNKNOWN
Classifier: Intended Audience :: Science/Research
Classifier: License :: OSI Approved :: MIT License
Classifier: Programming Language :: Python
Classifier: Programming Language :: Python :: 2
Classifier: Programming Language :: Python :: 2.7
Classifier: Programming Language :: Python :: 3
Classifier: Programming Language :: Python :: 3.5
Classifier: Programming Language :: Python :: 3.6
Classifier: Topic :: Scientific/Engineering
Classifier: Topic :: Scientific/Engineering :: Visualization
Requires-Python: >=2.7,!=3.0.*,!=3.1.*,!=3.2.*,!=3.3.*,!=3.4.*
